basil_core/__init__.py
basil_core/__version__.py
basil_core/array_tools/__init__.py
basil_core/array_tools/_indexer.cpython-312-x86_64-linux-musl.so
basil_core/array_tools/indexer.py
basil_core/astro/__init__.py
basil_core/astro/coordinates/__init__.py
basil_core/astro/coordinates/_coordinates.cpython-312-x86_64-linux-musl.so
basil_core/astro/coordinates/_spin.cpython-312-x86_64-linux-musl.so
basil_core/astro/coordinates/_tides.cpython-312-x86_64-linux-musl.so
basil_core/astro/coordinates/coordinates.py
basil_core/astro/orbit/_DWD_RLOF.cpython-312-x86_64-linux-musl.so
basil_core/astro/orbit/__init__.py
basil_core/astro/orbit/_decay.cpython-312-x86_64-linux-musl.so
basil_core/astro/orbit/_kepler.cpython-312-x86_64-linux-musl.so
basil_core/astro/orbit/decay.py
basil_core/astro/orbit/ecc_root_finder.py
basil_core/astro/orbit/orbit.py
basil_core/astro/priors/__init__.py
basil_core/astro/priors/callister_priors.py
basil_core/astro/relations/__init__.py
basil_core/astro/relations/AGND/AGND.py
basil_core/astro/relations/AGND/__init__.py
basil_core/astro/relations/AGND/Lyon2024/LICENSE.txt
basil_core/astro/relations/AGND/Lyon2024/Lyon2024AGNPhi.dat
basil_core/astro/relations/AGND/Lyon2024/__init__.py
basil_core/astro/relations/GSMF/Fontana.py
basil_core/astro/relations/GSMF/Furlong2015.py
basil_core/astro/relations/GSMF/Navarro.py
basil_core/astro/relations/GSMF/Weibel.py
basil_core/astro/relations/GSMF/__init__.py
basil_core/astro/relations/GSMF/utils.py
basil_core/astro/relations/IMF/IMF.py
basil_core/astro/relations/IMF/__init__.py
basil_core/astro/relations/MZR/MZR.py
basil_core/astro/relations/MZR/__init__.py
basil_core/astro/relations/MZR/utils.py
basil_core/astro/relations/NSC_frac_of_GSM/NSC_frac_of_GSM.py
basil_core/astro/relations/NSC_frac_of_GSM/__init__.py
basil_core/astro/relations/NSC_mass_of_GSM/NSC_mass_of_GSM.py
basil_core/astro/relations/NSC_mass_of_GSM/__init__.py
basil_core/astro/relations/SFRD/SFRD.py
basil_core-1.2.1.dist-info/METADATA
basil_core-1.2.1.dist-info/WHEEL
basil_core-1.2.1.dist-info/RECORD
