Metadata-Version: 2.1
Name: basil_core
Version: 1.2.1
Summary: BASIL-CORE: Bayesian Analytic Sampling and Integrating Library - Compiled and low-dependency utilities
Keywords: Gravitational Wave,Bayesian Inference
Author-Email: "V. Delfavero" <vdfavero@cita.utoronto.ca>
Maintainer-Email: "V. Delfavero" <vdfavero@cita.utoronto.ca>
License: MIT License
Classifier: Development Status :: 3 - Alpha
Classifier: Programming Language :: Python :: 3
Classifier: Operating System :: OS Independent
Classifier: Intended Audience :: Science/Research
Classifier: Topic :: Scientific/Engineering :: Astronomy
Classifier: Topic :: Scientific/Engineering :: Physics
Classifier: Topic :: Scientific/Engineering :: Information Analysis
Project-URL: Homepage, https://gitlab.com/xevra/basil-core
Project-URL: Bug tracker, https://gitlab.com/xevra/basil-core/issues
Requires-Python: >=3.12
Requires-Dist: h5py>=2.7.0
Requires-Dist: numpy<2.4.0,>=2.0
Requires-Dist: matplotlib>=2.2.4
Requires-Dist: scipy>=1.5.0
Requires-Dist: six>=1.10.0
Requires-Dist: fast_histogram>=0.10
Requires-Dist: xev-data>=0.1.1
Requires-Dist: astropy>=6.0
Requires-Dist: pathlib
